pyraingen/__init__.py
pyraingen/aggregaterainfall.py
pyraingen/computeifd.py
pyraingen/computesubdailykde.py
pyraingen/convert_daily_to_NetCDF.py
pyraingen/dailysequences.py
pyraingen/data/__init__.py
pyraingen/data/coefficients.dat
pyraingen/data/daily_logreg_coefs.csv
pyraingen/data/example/__init__.py
pyraingen/data/example/daily/__init__.py
pyraingen/data/example/daily/rev_dr061003.txt
pyraingen/data/example/daily/rev_dr061072.txt
pyraingen/data/example/daily/rev_dr061223.txt
pyraingen/data/example/daily/rev_dr066072.txt
pyraingen/data/example/daily/rev_dr066101.txt
pyraingen/data/example/ifd/__init__.py
pyraingen/data/example/ifd/subdaily.nc
pyraingen/data/example/ifd/targetifds.csv
pyraingen/data/example/subdaily/__init__.py
pyraingen/data/example/subdaily/daily.nc
pyraingen/data/example/subdaily/plv007080.nc
pyraingen/data/example/subdaily/plv061078.nc
pyraingen/data/example/subdaily/plv061152.nc
pyraingen/data/example/subdaily/plv061211.nc
pyraingen/data/example/subdaily/plv061223.nc
pyraingen/data/example/subdaily/plv061240.nc
pyraingen/data/example/subdaily/plv061351.nc
pyraingen/data/example/subdaily/plv063023.nc
pyraingen/data/example/subdaily/plv063039.nc
pyraingen/data/example/subdaily/plv063043.nc
pyraingen/data/example/subdaily/plv063108.nc
pyraingen/data/example/subdaily/plv063254.nc
pyraingen/data/example/subdaily/plv066037.nc
pyraingen/data/example/subdaily/plv066062.nc
pyraingen/data/example/subdaily/plv066063.nc
pyraingen/data/example/subdaily/plv066124.nc
pyraingen/data/example/subdaily/plv066137.nc
pyraingen/data/example/subdaily/plv066142.nc
pyraingen/data/example/subdaily/plv066164.nc
pyraingen/data/example/subdaily/plv067006.nc
pyraingen/data/example/subdaily/plv067033.nc
pyraingen/data/example/subdaily/plv067035.nc
pyraingen/data/example/subdaily/plv068102.nc
pyraingen/data/example/subdaily/plv068117.nc
pyraingen/data/example/subdaily/plv068131.nc
pyraingen/data/example/subdaily/plv070025.nc
pyraingen/data/example/subdaily/plv071063.nc
pyraingen-1.0.2.dist-info/WHEEL
pyraingen-1.0.2.dist-info/METADATA
pyraingen-1.0.2.dist-info/RECORD
