Metadata-Version: 2.1
Name: pyraingen
Version: 1.0.2
Summary: A package for stochastically generating daily and subdaily rainfall in Australia with ifd constraining.
License: None
Author: Caleb Dykman
Requires-Python: ==3.8.5
Classifier: License :: Other/Proprietary License
Classifier: Programming Language :: Python :: 3
Requires-Dist: joblib (==1.4.2)
Requires-Dist: matplotlib (==3.6.2)
Requires-Dist: netCDF4 (==1.6.2)
Requires-Dist: numba (==0.56.4)
Requires-Dist: numpy (==1.23.5)
Requires-Dist: pandas (==1.5.3)
Requires-Dist: scipy (==1.9.3)
Requires-Dist: xarray (==2023.01.0)
